[{"datetime": "2026-01-19 00:00:00", "open": 5898.5, "high": 5970.0, "low": 5879.0, "close": 5943.5, "volume": 145915}, {"datetime": "2026-01-20 00:00:00", "open": 5943.5, "high": 5994.5, "low": 5862.0, "close": 5884.0, "volume": 350070}, {"datetime": "2026-01-21 00:00:00", "open": 5870.0, "high": 5899.0, "low": 5787.0, "close": 5802.5, "volume": 662863}, {"datetime": "2026-01-22 00:00:00", "open": 5850.0, "high": 5975.0, "low": 5819.0, "close": 5932.0, "volume": 435081}, {"datetime": "2026-01-23 00:00:00", "open": 5950.0, "high": 5964.0, "low": 5813.5, "close": 5835.0, "volume": 142248}]