[{"datetime": "2026-01-19 00:00:00", "open": 7994.0, "high": 8110.0, "low": 7949.5, "close": 8066.5, "volume": 8887}, {"datetime": "2026-01-20 00:00:00", "open": 8066.5, "high": 8067.0, "low": 7829.0, "close": 7893.0, "volume": 20695}, {"datetime": "2026-01-21 00:00:00", "open": 7893.0, "high": 8144.5, "low": 7833.0, "close": 8093.5, "volume": 30583}, {"datetime": "2026-01-22 00:00:00", "open": 8090.0, "high": 8100.0, "low": 7940.0, "close": 8049.5, "volume": 47643}, {"datetime": "2026-01-23 00:00:00", "open": 8049.5, "high": 8075.5, "low": 7912.0, "close": 7986.5, "volume": 17235}]